rsyncdaemon/__init__.py
rsyncdaemon/confbuilder.py
rsyncdaemon/rsyncdaemon.py
rsyncdaemon-0.0.1.dist-info/LICENSE
rsyncdaemon-0.0.1.dist-info/METADATA
rsyncdaemon-0.0.1.dist-info/WHEEL
rsyncdaemon-0.0.1.dist-info/entry_points.txt
rsyncdaemon-0.0.1.dist-info/top_level.txt
rsyncdaemon-0.0.1.dist-info/RECORD
