Metadata-Version: 2.1
Name: rsyncdaemon
Version: 0.0.1
Summary: Python based CLI Remote Syncing Daemon service.
Author-email: Pankaj Jackson <pankajackson@live.co.uk>
License: GNU GENERAL PUBLIC LICENSE
Project-URL: Homepage, https://github.com/pankajackson/RSyncDaemon
Project-URL: Bug Tracker, https://github.com/pankajackson/RSyncDaemon/issues
Project-URL: Source, https://github.com/pankajackson/RSyncDaemon
Keywords: rsync,sync,transfer,backup
Classifier: Programming Language :: Python :: 3
Classifier: Development Status :: 4 - Beta
Classifier: Intended Audience :: System Administrators
Classifier: License :: OSI Approved :: GNU General Public License v3 or later (GPLv3+)
Classifier: Operating System :: Unix
Requires-Python: >=3.7
License-File: LICENSE
Requires-Dist: paramiko
Requires-Dist: watchdog
Requires-Dist: toml
